image_viewer-0.0.2.data/data/data/fonts/DroidSansMono.ttf
iview/__init__.py
iview/__main__.py
iview/color.py
iview/config.py
iview/draw_text.py
iview/image_paths.py
iview/image_processor.py
iview/image_ring.py
iview/image_utils.py
iview/iview.py
iview/keys.py
iview/paths.py
iview/type_ext.py
iview/ui.py
iview/window.py
lib/__init__.py
lib/cli.py
lib/ring_buffer.py
lib/util.py
image_viewer-0.0.2.dist-info/LICENSE
image_viewer-0.0.2.dist-info/METADATA
image_viewer-0.0.2.dist-info/WHEEL
image_viewer-0.0.2.dist-info/entry_points.txt
image_viewer-0.0.2.dist-info/top_level.txt
image_viewer-0.0.2.dist-info/RECORD
